dj_set_downloader/__init__.py
dj_set_downloader/api_client.py
dj_set_downloader/api_response.py
dj_set_downloader/configuration.py
dj_set_downloader/exceptions.py
dj_set_downloader/rest.py
dj_set_downloader/api/__init__.py
dj_set_downloader/api/downloads_api.py
dj_set_downloader/api/jobs_api.py
dj_set_downloader/api/process_api.py
dj_set_downloader/api/system_api.py
dj_set_downloader/docs/DomainTrack.md
dj_set_downloader/docs/DomainTracklist.md
dj_set_downloader/docs/DownloadsApi.md
dj_set_downloader/docs/JobRequest.md
dj_set_downloader/docs/JobResponse.md
dj_set_downloader/docs/JobStatus.md
dj_set_downloader/docs/JobTracksInfoResponse.md
dj_set_downloader/docs/JobsApi.md
dj_set_downloader/docs/ProcessApi.md
dj_set_downloader/docs/ProgressEvent.md
dj_set_downloader/docs/ProgressStage.md
dj_set_downloader/docs/ProgressTrackDetails.md
dj_set_downloader/docs/ServerCancelResponse.md
dj_set_downloader/docs/ServerErrorResponse.md
dj_set_downloader/docs/ServerHealthResponse.md
dj_set_downloader/docs/ServerProcessResponse.md
dj_set_downloader/docs/SystemApi.md
dj_set_downloader/models/__init__.py
dj_set_downloader/models/domain_track.py
dj_set_downloader/models/domain_tracklist.py
dj_set_downloader/models/job_request.py
dj_set_downloader/models/job_response.py
dj_set_downloader/models/job_status.py
dj_set_downloader/models/job_tracks_info_response.py
dj_set_downloader/models/progress_event.py
dj_set_downloader/models/progress_stage.py
dj_set_downloader/models/progress_track_details.py
dj_set_downloader/models/server_cancel_response.py
dj_set_downloader/models/server_error_response.py
dj_set_downloader/models/server_health_response.py
dj_set_downloader/models/server_process_response.py
dj_set_downloader/test/__init__.py
dj_set_downloader/test/test_domain_track.py
dj_set_downloader/test/test_domain_tracklist.py
dj_set_downloader/test/test_downloads_api.py
dj_set_downloader/test/test_job_request.py
dj_set_downloader/test/test_job_response.py
dj_set_downloader-0.1.3.dist-info/METADATA
dj_set_downloader-0.1.3.dist-info/WHEEL
dj_set_downloader-0.1.3.dist-info/RECORD
